<observationResults name="une sortie Mobidyc" nbReplicat="2" nbExp="10">
    <date name="date1" unit="jour">
      <variable name="moyTailMaxFem" type="float" sep=" "  nbExp="10" nbReplicat="2" leng="1">
         57.9332  53.4599 54.8241 55.7852 55.008 54.9579 53.3819 54.1589 53.3658 58.4322 57.9332  53.4599 54.8241 55.7852 55.008 54.9579 53.3819 54.1589 53.3658 58.4322
      </variable>
      <variable name="moyTaillMaxMal" type="float" sep=" " nbExp="10" nbReplicat="2" leng="1">
         24.9125 24.0581 24.9128 25.5737 24.4704 25.697 26.1449 25.9035 25.4705 24.0121 24.9125 24.0581 24.9128 25.5737 24.4704 25.697 26.1449 25.9035 25.4705 24.012      </variable>      
       <variable name="nombreMales" type="float" nbExp="10" nbReplicat="2" leng="1"> 
        30.0 28.0 16.0 28.0 31.0 34.0 32.0 24.0 32.0 28.0 30.0 28.0 16.0 28.0 31.0 34.0 32.0 24.0 32.0 28.0      
       </variable>
    </date>
 </observationResults >